crystalflow/__init__.py
crystalflow/atom_emb.py
crystalflow/parser.py
crystalflow/utils.py
crystalflow-0.0.9.dist-info/METADATA
crystalflow-0.0.9.dist-info/WHEEL
crystalflow-0.0.9.dist-info/top_level.txt
crystalflow-0.0.9.dist-info/RECORD
